{
    "width": 1200,
    "height": 600,
    "startLocation": "region2_abandodedHuntersCamp",
    "regions": {
        "1": {
            "regionId": 1,
            "name": "Дубовый лес",
            "x": 100, 
            "y": 200,
            "resourceLocations": ["forest", "forest"],
            "locations": [
                "region2_sawmill",
                "region2_abandodedHuntersCamp",
                "region2_huntersCamp"
            ]
        },
        "2": {
            "regionId": 2,
            "name": "Предлесье",
            "x": 350,
            "y": 150,
            "resourceLocations": ["plain", "plain", "plain"],
            "locations": [
            ]
        },
        "3": {
            "regionId": 3,
            "name": "-",
            "x": 550,
            "y": 100,
            "resourceLocations": ["plain", "plain", "forest"],
            "locations": []
        },
        "4": {
            "regionId": 4,
            "name": "-",
            "x": 500,
            "y": 350,
            "resourceLocations": ["plain", "plain", "forest"],
            "locations": []
        }
    },
    "roads": [
        {   
            "regions": [1,2],
            "travelTime": 2
        },
        {
            "regions": [2,3],
            "travelTime": 3
        },
        {
            "regions" : [2,4],
            "travelTime": 3
        }
    ]
}


